loanpy/__init__.py
loanpy/eval_sca.py
loanpy/ipa_all.csv
loanpy/loanfinder.py
loanpy/scapplier.py
loanpy/scminer.py
loanpy/utils.py
loanpy-3.0.1.data/data/loanpy/ipa_all.csv
loanpy-3.0.1.dist-info/LICENSE
loanpy-3.0.1.dist-info/METADATA
loanpy-3.0.1.dist-info/WHEEL
loanpy-3.0.1.dist-info/top_level.txt
loanpy-3.0.1.dist-info/RECORD
