Metadata-Version: 2.1
Name: loanpy
Version: 3.0.1
Summary: a linguistic toolkit for detecting old loanwords by predicting,evaluating and applying changes in horizontal and vertical lexical transfers
Home-page: https://github.com/martino-vic/loanpy
Download-URL: https://github.com/LoanpyDataHub/loanpy/archive/3.0.0.tar.gz
Author: Viktor Martinović
Author-email: viktor_martinovic@eva.mpg.de
License: MIT
Project-URL: documentation, https://loanpy.readthedocs.io/en/latest/home.html
Project-URL: citation, https://zenodo.org/record/7893906
Project-URL: continuous integration, https://dl.circleci.com/status-badge/redirect/gh/LoanpyDataHub/loanpy/tree/main
Project-URL: test coverage, https://coveralls.io/github/LoanpyDataHub/loanpy
Project-URL: database, https://github.com/LoanpyDataHub
Keywords: linguistics,loanwords,language-contact,sound-change-applier
Platform: Windows
Platform: macOS
Platform: Linux
Classifier: Development Status :: 3 - Alpha
Classifier: Intended Audience :: Science/Research
Classifier: Topic :: Scientific/Engineering
Classifier: Topic :: Text Processing :: Linguistic
Classifier: License :: OSI Approved :: MIT License
Classifier: Natural Language :: English
Classifier: Operating System :: MacOS
Classifier: Operating System :: Microsoft :: Windows
Classifier: Operating System :: POSIX :: Linux
Classifier: Programming Language :: Python :: 3.7
Classifier: Programming Language :: Python :: 3.8
Classifier: Programming Language :: Python :: 3.9
Classifier: Programming Language :: Python :: 3.10
Classifier: Programming Language :: Python :: 3.11
Requires-Python: >=3.7
License-File: LICENSE
Provides-Extra: dev
Requires-Dist: wheel ; extra == 'dev'
Requires-Dist: twine ; extra == 'dev'
Requires-Dist: sphinx ; extra == 'dev'
Provides-Extra: test
Requires-Dist: pytest (>=7.1.2) ; extra == 'test'
Requires-Dist: coverage (>=7.2.2) ; extra == 'test'
